ggvlib/__init__.py
ggvlib/appsflyer/__init__.py
ggvlib/appsflyer/api.py
ggvlib/config.py
ggvlib/google/__init__.py
ggvlib/google/bigquery.py
ggvlib/google/cloudsql.py
ggvlib/google/drive.py
ggvlib/google/forms.py
ggvlib/google/people.py
ggvlib/google/pubsub.py
ggvlib/google/scheduler.py
ggvlib/google/schemas.py
ggvlib/google/secrets.py
ggvlib/google/sheets.py
ggvlib/google/storage.py
ggvlib/google/utils.py
ggvlib/hubspot/__init__.py
ggvlib/hubspot/api.py
ggvlib/hubspot/schemas.py
ggvlib/io/__init__.py
ggvlib/io/files.py
ggvlib/io/json.py
ggvlib/io/yaml.py
ggvlib/logging.py
ggvlib/mixpanel/__init__.py
ggvlib/mixpanel/api.py
ggvlib/parsing.py
ggvlib/productivity/__init__.py
ggvlib/productivity/decorators.py
ggvlib/productivity/jobs.py
ggvlib/reporting/__init__.py
ggvlib/reporting/mail.py
ggvlib/twilio/__init__.py
ggvlib/twilio/api.py
ggvlib/twilio/parsing.py
ggvlib-0.2.56.dist-info/METADATA
ggvlib-0.2.56.dist-info/WHEEL
ggvlib-0.2.56.dist-info/RECORD
