Metadata-Version: 2.1
Name: ggvlib
Version: 0.2.56
Summary: 
Author: Adam Hoffstein
Author-email: adam.hoffstein@gogox.com
Requires-Python: >=3.8,<3.11
Classifier: Programming Language :: Python :: 3
Classifier: Programming Language :: Python :: 3.8
Classifier: Programming Language :: Python :: 3.9
Classifier: Programming Language :: Python :: 3.10
Requires-Dist: aiohttp (>=3.8.3,<4.0.0)
Requires-Dist: cloud-sql-python-connector (>=1.11.0,<2.0.0)
Requires-Dist: db-dtypes (>=1.0.4,<2.0.0)
Requires-Dist: google-api-python-client (>=2.65.0,<3.0.0)
Requires-Dist: google-auth-oauthlib (>=0.8.0,<0.9.0)
Requires-Dist: google-cloud-bigquery (>=3.3.5,<4.0.0)
Requires-Dist: google-cloud-bigquery-storage (>=2.16.2,<3.0.0)
Requires-Dist: google-cloud-pubsub (>=2.14.0,<3.0.0)
Requires-Dist: google-cloud-scheduler (>=2.7.3,<3.0.0)
Requires-Dist: google-cloud-secret-manager (>=2.12.6,<3.0.0)
Requires-Dist: google-cloud-storage (>=2.5.0,<3.0.0)
Requires-Dist: google-crc32c (>=1.5.0,<2.0.0)
Requires-Dist: jsonschema (>=4.17.0,<5.0.0)
Requires-Dist: loguru (>0.5.0)
Requires-Dist: pandas (>=1.5.1,<3)
Requires-Dist: pg8000 (>=1.31.2,<2.0.0)
Requires-Dist: pydantic (>=1.10.2,<2.0.0)
Requires-Dist: pyyaml (>=6.0,<7.0)
Requires-Dist: sendgrid (>=6.9.7,<7.0.0)
Requires-Dist: sqlalchemy (>=2.0.31,<3.0.0)
